{"name":"Crucible-client-scala","tagline":"crucible REST API client for scala","body":"# crucible rest api for scala\r\n\r\n[![Build Status](https://drone.io/github.com/ogrodnek/crucible-client-scala/status.png)](https://drone.io/github.com/ogrodnek/crucible-client-scala/latest)\r\n\r\nBasic api client for [Crucible](https://www.atlassian.com/software/crucible/overview)'s [REST API](https://docs.atlassian.com/fisheye-crucible/latest/wadl/crucible.html)\r\n","google":"","note":"Don't delete this file! It's used internally to help with page regeneration."}